odoo8_addon_l10n_es_dua-8.0.1.0.0.99.dev10-py3.6-nspkg.pth
odoo_addons/l10n_es_dua/README.rst
odoo_addons/l10n_es_dua/__init__.py
odoo_addons/l10n_es_dua/__openerp__.py
odoo_addons/l10n_es_dua/data/fiscal_position_taxes_dua.xml
odoo_addons/l10n_es_dua/data/fiscal_positions_dua.xml
odoo_addons/l10n_es_dua/data/products_dua.xml
odoo_addons/l10n_es_dua/data/taxes_dua.xml
odoo_addons/l10n_es_dua/i18n/ca.po
odoo_addons/l10n_es_dua/i18n/es.po
odoo_addons/l10n_es_dua/i18n/l10n_es_dua.pot
odoo_addons/l10n_es_dua/static/description/icon.png
odoo8_addon_l10n_es_dua-8.0.1.0.0.99.dev10.dist-info/METADATA
odoo8_addon_l10n_es_dua-8.0.1.0.0.99.dev10.dist-info/WHEEL
odoo8_addon_l10n_es_dua-8.0.1.0.0.99.dev10.dist-info/namespace_packages.txt
odoo8_addon_l10n_es_dua-8.0.1.0.0.99.dev10.dist-info/top_level.txt
odoo8_addon_l10n_es_dua-8.0.1.0.0.99.dev10.dist-info/RECORD
